main.py
git_fixup_commands-1.0.2.dist-info/METADATA
git_fixup_commands-1.0.2.dist-info/WHEEL
git_fixup_commands-1.0.2.dist-info/entry_points.txt
git_fixup_commands-1.0.2.dist-info/licenses/LICENSE
git_fixup_commands-1.0.2.dist-info/RECORD
