Metadata-Version: 2.4
Name: git-fixup-commands
Version: 1.0.2
Summary: A suite of Git commands to easily edit any previous commits via `git commit --fixup` and `git rebase --autosquash`.
Project-URL: homepage, https://www.brandonfowler.me/git-fixup-commands/
Project-URL: source, https://github.com/BrandonXLF/git-fixup-commands/
Project-URL: issues, https://github.com/BrandonXLF/git-fixup-commands/issues/
Author: Brandon Fowler
License-Expression: GPL-2.0-only
License-File: LICENSE
Keywords: amend,commit,edit,fixup,git,rebase,reword
Classifier: Development Status :: 5 - Production/Stable
Classifier: Environment :: Console
Classifier: Intended Audience :: Developers
Classifier: License :: OSI Approved :: GNU General Public License v2 (GPLv2)
Classifier: Programming Language :: Python :: 3
Classifier: Programming Language :: Python :: 3.7
Classifier: Programming Language :: Python :: 3.8
Classifier: Programming Language :: Python :: 3.9
Classifier: Programming Language :: Python :: 3.10
Classifier: Programming Language :: Python :: 3.11
Classifier: Programming Language :: Python :: 3.12
Classifier: Programming Language :: Python :: 3.13
Classifier: Programming Language :: Python :: 3.14
Classifier: Topic :: Software Development :: Version Control
Classifier: Topic :: Software Development :: Version Control :: Git
Requires-Python: >=3.7
